iotile/__init__.py
iotile/emulate/__init__.py
iotile/emulate/common/__init__.py
iotile/emulate/common/emulator_errors.py
iotile/emulate/constants/__init__.py
iotile/emulate/constants/const_subsystems.py
iotile/emulate/constants/const_tilemanager.py
iotile/emulate/constants/errors.py
iotile/emulate/constants/rpc_clockmanager.py
iotile/emulate/constants/rpc_config_database.py
iotile/emulate/constants/rpc_config_variables.py
iotile/emulate/constants/rpc_controller.py
iotile/emulate/constants/rpc_sensorgraph.py
iotile/emulate/constants/rpc_sensorlog.py
iotile/emulate/constants/rpc_tilemanager.py
iotile/emulate/constants/rpcs.py
iotile/emulate/constants/streams.py
iotile/emulate/demo/__init__.py
iotile/emulate/demo/demo_device.py
iotile/emulate/demo/demo_proxy.py
iotile/emulate/demo/demo_reference.py
iotile/emulate/internal/__init__.py
iotile/emulate/internal/emulation_loop.py
iotile/emulate/internal/response.py
iotile/emulate/internal/rpc_queue.py
iotile/emulate/reference/__init__.py
iotile/emulate/reference/reference_controller.py
iotile/emulate/reference/reference_device.py
iotile/emulate/reference/controller_features/__init__.py
iotile/emulate/reference/controller_features/clock_manager.py
iotile/emulate/reference/controller_features/config_database.py
iotile/emulate/reference/controller_features/controller_system.py
iotile/emulate/reference/controller_features/remote_bridge.py
iotile/emulate/reference/controller_features/sensor_graph.py
iotile/emulate/reference/controller_features/sensor_log.py
iotile/emulate/reference/controller_features/stream_manager.py
iotile/emulate/reference/controller_features/tile_manager.py
iotile/emulate/transport/__init__.py
iotile/emulate/transport/emulatedadapter.py
iotile/emulate/utilities/__init__.py
iotile/emulate/utilities/format_rpc.py
iotile/emulate/virtual/__init__.py
iotile/emulate/virtual/emulated_device.py
iotile/emulate/virtual/emulated_tile.py
iotile/emulate/virtual/emulation_mixin.py
iotile_emulate-0.6.0.dist-info/LICENSE.md
iotile_emulate-0.6.0.dist-info/METADATA
iotile_emulate-0.6.0.dist-info/WHEEL
iotile_emulate-0.6.0.dist-info/entry_points.txt
iotile_emulate-0.6.0.dist-info/top_level.txt
iotile_emulate-0.6.0.dist-info/RECORD
